[{"DATE":"2026-03-17","prob_percent":0.01},{"DATE":"2026-03-18","prob_percent":0.01},{"DATE":"2026-03-19","prob_percent":0.06},{"DATE":"2026-03-20","prob_percent":0.1},{"DATE":"2026-03-21","prob_percent":0.27},{"DATE":"2026-03-22","prob_percent":0.68},{"DATE":"2026-03-23","prob_percent":1.24},{"DATE":"2026-03-24","prob_percent":2.06},{"DATE":"2026-03-25","prob_percent":3.38},{"DATE":"2026-03-26","prob_percent":4.51},{"DATE":"2026-03-27","prob_percent":7.26},{"DATE":"2026-03-28","prob_percent":8.42},{"DATE":"2026-03-29","prob_percent":9.55},{"DATE":"2026-03-30","prob_percent":11.33},{"DATE":"2026-03-31","prob_percent":11.67},{"DATE":"2026-04-01","prob_percent":10.13},{"DATE":"2026-04-02","prob_percent":9.16},{"DATE":"2026-04-03","prob_percent":6.96},{"DATE":"2026-04-04","prob_percent":5.05},{"DATE":"2026-04-05","prob_percent":3.51},{"DATE":"2026-04-06","prob_percent":2.35},{"DATE":"2026-04-07","prob_percent":1.13},{"DATE":"2026-04-08","prob_percent":0.63},{"DATE":"2026-04-09","prob_percent":0.26},{"DATE":"2026-04-10","prob_percent":0.2},{"DATE":"2026-04-11","prob_percent":0.04},{"DATE":"2026-04-12","prob_percent":0.03}]